<?xml version="1.0" ?>
<Template>
  <Gravity type="float" default="130" description="" />
  <GroundOffset type="float" default="0" description="" />
  <InitVel type="float" default="15" description="" />
  <IsCastShadow type="bool" default="false" description="" />
  <JumpVel type="float" default="40" description="" />
  <Range type="float" default="100" description="" />
  <SideBreak type="float" default="50" description="" />
  <SideVel type="float" default="25" description="" />
  <TimeAccel type="float" default="2.1" description="" />
  <TimeBreak type="float" default="4.2" description="" />
  <VelMax type="float" default="120" description="" />
  <VelMin type="float" default="30" description="" />
</Template>
